djsentoo/__init__.py
djsentoo/admin.py
djsentoo/apps.py
djsentoo/config.py
djsentoo/forms.py
djsentoo/models.py
djsentoo/service.py
djsentoo/signals.py
djsentoo/tests.py
djsentoo/urls.py
djsentoo/views.py
djsentoo/migrations/0001_initial.py
djsentoo/migrations/0002_alter_transaction_currency.py
djsentoo/migrations/0003_alter_transaction_currency.py
djsentoo/migrations/0004_alter_transaction_currency_alter_transaction_status.py
djsentoo/migrations/__init__.py
djsentoo-0.2.2.dist-info/METADATA
djsentoo-0.2.2.dist-info/WHEEL
djsentoo-0.2.2.dist-info/RECORD
