Metadata-Version: 2.4
Name: djsentoo
Version: 0.2.2
Summary: A reusable Django app for integrating with the Sentoo payment gateway.
Project-URL: Homepage, https://github.com/rhymiz/djsentoo
Project-URL: GitHub, https://github.com/rhymiz/djsentoo
Author-email: Lemi Boyce <lemuel@vokality.com>
License-Expression: MIT
Keywords: aruba,bonaire,curacao,django,ecommerce,payment gateway,payments,sentoo,sint eustatius,sint maarten
Classifier: Development Status :: 5 - Production/Stable
Classifier: Framework :: Django :: 5
Classifier: Framework :: Django :: 5.0
Classifier: Framework :: Django :: 5.1
Classifier: Framework :: Django :: 5.2
Classifier: License :: OSI Approved :: MIT License
Classifier: Programming Language :: Python :: 3
Classifier: Programming Language :: Python :: 3.12
Classifier: Programming Language :: Python :: 3.13
Classifier: Programming Language :: Python :: 3.14
Classifier: Topic :: Software Development :: Libraries
Requires-Python: >=3.12
Requires-Dist: django>=5.2.1
Requires-Dist: sentoo>=0.2.0
